argparsetree/__init__.py
argparsetree/cmd.py
argparsetree-0.0.6.dist-info/DESCRIPTION.rst
argparsetree-0.0.6.dist-info/METADATA
argparsetree-0.0.6.dist-info/RECORD
argparsetree-0.0.6.dist-info/WHEEL
argparsetree-0.0.6.dist-info/metadata.json
argparsetree-0.0.6.dist-info/top_level.txt
