Metadata-Version: 2.0
Name: argparsetree
Version: 0.0.6
Summary: Package for creating complex command line argument trees using argparse
Home-page: https://github.com/wildfish/argparsetree
Author: Wildfish
Author-email: developers@wildfish.com
License: MIT
Keywords: class based argparse
Platform: UNKNOWN
Classifier: Development Status :: 4 - Beta
Classifier: License :: OSI Approved :: BSD License
Classifier: Operating System :: OS Independent
Classifier: Programming Language :: Python
Classifier: Programming Language :: Python :: 2.7
Classifier: Programming Language :: Python :: 3
Classifier: Programming Language :: Python :: 3.5
Classifier: Programming Language :: Python :: 3.6
